[{"name":"Joanna","lastName":"Waniorek","gender":"k","age":18,"mail":"joanna.waniorek@gmail.com","phoneNumber":"186-468-704","PESEL":"023209341010"},{"name":"Barbara","lastName":"Siejak","gender":"k","age":18,"mail":"barbara.siejak@gmail.com","phoneNumber":"053-523-130","PESEL":"02301345901"},{"name":"Barbara","lastName":"Gromada","gender":"k","age":51,"mail":"barbara.gromada@gmail.com","phoneNumber":"421-807-808","PESEL":"69102623122"},{"name":"Bartosz","lastName":"Waniorek","gender":"m","age":57,"mail":"bartosz.waniorek@gmail.com","phoneNumber":"376-418-875","PESEL":"63092584593"},{"name":"Bartłomiej","lastName":"Gromada","gender":"m","age":58,"mail":"bartłomiej.gromada@wp.pl","phoneNumber":"132-601-221","PESEL":"620501632310"},{"name":"Krzysztof","lastName":"Waniorek","gender":"m","age":37,"mail":"krzysztof.waniorek@gmail.com","phoneNumber":"068-432-047","PESEL":"830622659510"},{"name":"Krzysztof","lastName":"Waniorek","gender":"m","age":64,"mail":"waniorek.krzysztof@gmail.com","phoneNumber":"684-013-362","PESEL":"56022849332"},{"name":"Tomasz","lastName":"Gromada","gender":"m","age":24,"mail":"tomasz.gromada@wp.pl","phoneNumber":"587-020-581","PESEL":"96060299832"},{"name":"Bartłomiej","lastName":"Gromada","gender":"m","age":62,"mail":"bartłomiej.gromada@onet.pl","phoneNumber":"741-205-403","PESEL":"580609645910"},{"name":"Joanna","lastName":"Waniorek","gender":"k","age":19,"mail":"joanna.waniorek@onet.pl","phoneNumber":"265-611-380","PESEL":"01221546526"},{"name":"Tomasz","lastName":"Waniorek","gender":"m","age":15,"mail":"tomasz.waniorek@wp.pl","phoneNumber":"112-478-727","PESEL":"05261084813"},{"name":"Katarzyna","lastName":"Siejak","gender":"k","age":47,"mail":"katarzyna.siejak@gmail.com","phoneNumber":"830-182-147","PESEL":"73100845727"},{"name":"Joanna","lastName":"Gromada","gender":"k","age":39,"mail":"joanna.gromada@o2.pl","phoneNumber":"046-714-683","PESEL":"81070963246"},{"name":"Katarzyna","lastName":"Siejak","gender":"k","age":60,"mail":"siejak.katarzyna@gmail.com","phoneNumber":"762-054-832","PESEL":"60020761103"},{"name":"Joanna","lastName":"Siejak","gender":"k","age":53,"mail":"joanna.siejak@gmail.com","phoneNumber":"813-161-668","PESEL":"67122686343"},{"name":"Bartłomiej","lastName":"Waniorek","gender":"m","age":61,"mail":"bartłomiej.waniorek@onet.pl","phoneNumber":"050-475-412","PESEL":"59092188776"},{"name":"Bartłomiej","lastName":"Siejak","gender":"m","age":46,"mail":"bartłomiej.siejak@onet.pl","phoneNumber":"426-747-622","PESEL":"74102796134"},{"name":"Bartosz","lastName":"Siejak","gender":"m","age":56,"mail":"bartosz.siejak@wp.pl","phoneNumber":"540-580-828","PESEL":"64010291494"},{"name":"Katarzyna","lastName":"Gromada","gender":"k","age":34,"mail":"katarzyna.gromada@o2.pl","phoneNumber":"504-025-870","PESEL":"86020195746"},{"name":"Krzysztof","lastName":"Waniorek","gender":"m","age":33,"mail":"krzysztof.waniorek1@gmail.com","phoneNumber":"734-184-131","PESEL":"87021717452"},{"name":"Bartłomiej","lastName":"Waniorek","gender":"m","age":41,"mail":"bartłomiej.waniorek@gmail.com","phoneNumber":"544-263-738","PESEL":"79021043972"},{"name":"Katarzyna","lastName":"Waniorek","gender":"k","age":23,"mail":"katarzyna.waniorek@gmail.com","phoneNumber":"262-240-375","PESEL":"970429878610"},{"name":"Bartłomiej","lastName":"Siejak","gender":"m","age":60,"mail":"bartłomiej.siejak@gmail.com","phoneNumber":"745-760-117","PESEL":"60051413415"},{"name":"Katarzyna","lastName":"Siejak","gender":"k","age":64,"mail":"katarzyna.siejak@o2.pl","phoneNumber":"070-837-872","PESEL":"56061815624"},{"name":"Joanna","lastName":"Waniorek","gender":"k","age":44,"mail":"waniorek.joanna@onet.pl","phoneNumber":"178-706-613","PESEL":"76030124401"},{"name":"Krzysztof","lastName":"Gromada","gender":"m","age":23,"mail":"krzysztof.gromada@wp.pl","phoneNumber":"111-806-531","PESEL":"97062065915"},{"name":"Barbara","lastName":"Waniorek","gender":"k","age":22,"mail":"barbara.waniorek@wp.pl","phoneNumber":"074-872-471","PESEL":"98091197488"},{"name":"Katarzyna","lastName":"Gromada","gender":"k","age":53,"mail":"katarzyna.gromada@gmail.com","phoneNumber":"732-165-607","PESEL":"67050199148"},{"name":"Barbara","lastName":"Siejak","gender":"k","age":15,"mail":"siejak.barbara@gmail.com","phoneNumber":"214-585-372","PESEL":"05310679304"},{"name":"Krzysztof","lastName":"Waniorek","gender":"m","age":46,"mail":"krzysztof.waniorek@wp.pl","phoneNumber":"777-760-702","PESEL":"74031085538"},{"name":"Joanna","lastName":"Gromada","gender":"k","age":55,"mail":"joanna.gromada@wp.pl","phoneNumber":"734-711-402","PESEL":"65010174644"},{"name":"Bartłomiej","lastName":"Waniorek","gender":"m","age":59,"mail":"bartłomiej.waniorek@wp.pl","phoneNumber":"747-528-722","PESEL":"61042316997"},{"name":"Krzysztof","lastName":"Siejak","gender":"m","age":38,"mail":"krzysztof.siejak@onet.pl","phoneNumber":"654-167-430","PESEL":"82070649297"},{"name":"Krzysztof","lastName":"Siejak","gender":"m","age":38,"mail":"siejak.krzysztof@onet.pl","phoneNumber":"662-372-588","PESEL":"82111352137"},{"name":"Joanna","lastName":"Siejak","gender":"k","age":33,"mail":"joanna.siejak@wp.pl","phoneNumber":"152-163-035","PESEL":"87081356765"},{"name":"Bartłomiej","lastName":"Gromada","gender":"m","age":33,"mail":"gromada.bartłomiej@wp.pl","phoneNumber":"635-822-141","PESEL":"87063054454"},{"name":"Tomasz","lastName":"Siejak","gender":"m","age":29,"mail":"tomasz.siejak@wp.pl","phoneNumber":"721-388-701","PESEL":"91020446211"},{"name":"Joanna","lastName":"Siejak","gender":"k","age":56,"mail":"joanna.siejak@o2.pl","phoneNumber":"335-177-131","PESEL":"640321437610"},{"name":"Bartłomiej","lastName":"Gromada","gender":"m","age":64,"mail":"bartłomiej.gromada1@wp.pl","phoneNumber":"711-747-344","PESEL":"56112684276"},{"name":"Bartłomiej","lastName":"Gromada","gender":"m","age":34,"mail":"bartłomiej.gromada2@wp.pl","phoneNumber":"824-555-818","PESEL":"86061577958"},{"name":"Tomasz","lastName":"Gromada","gender":"m","age":39,"mail":"gromada.tomasz@wp.pl","phoneNumber":"664-164-535","PESEL":"811111718110"},{"name":"Bartłomiej","lastName":"Siejak","gender":"m","age":21,"mail":"bartłomiej.siejak@wp.pl","phoneNumber":"607-731-172","PESEL":"99061324611"},{"name":"Katarzyna","lastName":"Waniorek","gender":"k","age":28,"mail":"katarzyna.waniorek@wp.pl","phoneNumber":"242-176-407","PESEL":"92092229582"},{"name":"Barbara","lastName":"Gromada","gender":"k","age":19,"mail":"barbara.gromada@o2.pl","phoneNumber":"558-271-883","PESEL":"01290465607"},{"name":"Bartosz","lastName":"Siejak","gender":"m","age":29,"mail":"bartosz.siejak@onet.pl","phoneNumber":"616-552-480","PESEL":"91052364271"},{"name":"Barbara","lastName":"Gromada","gender":"k","age":15,"mail":"gromada.barbara@o2.pl","phoneNumber":"085-111-586","PESEL":"05251099186"},{"name":"Bartosz","lastName":"Waniorek","gender":"m","age":34,"mail":"bartosz.waniorek@onet.pl","phoneNumber":"867-054-528","PESEL":"86031923817"},{"name":"Barbara","lastName":"Gromada","gender":"k","age":27,"mail":"barbara.gromada@onet.pl","phoneNumber":"500-157-237","PESEL":"93092375341"},{"name":"Bartosz","lastName":"Waniorek","gender":"m","age":48,"mail":"waniorek.bartosz@onet.pl","phoneNumber":"450-017-006","PESEL":"72012212654"},{"name":"Tomasz","lastName":"Waniorek","gender":"m","age":29,"mail":"waniorek.tomasz@wp.pl","phoneNumber":"602-412-451","PESEL":"91052749575"},{"name":"Krzysztof","lastName":"Gromada","gender":"m","age":56,"mail":"krzysztof.gromada@onet.pl","phoneNumber":"623-826-130","PESEL":"64012632752"},{"name":"Katarzyna","lastName":"Gromada","gender":"k","age":49,"mail":"gromada.katarzyna@o2.pl","phoneNumber":"442-388-344","PESEL":"71101612283"},{"name":"Katarzyna","lastName":"Gromada","gender":"k","age":15,"mail":"katarzyna.gromada@onet.pl","phoneNumber":"811-262-535","PESEL":"05300694601"},{"name":"Krzysztof","lastName":"Waniorek","gender":"m","age":51,"mail":"waniorek.krzysztof@wp.pl","phoneNumber":"171-762-423","PESEL":"69031518159"},{"name":"Bartłomiej","lastName":"Siejak","gender":"m","age":42,"mail":"bartłomiej.siejak@o2.pl","phoneNumber":"075-553-514","PESEL":"78011276932"},{"name":"Barbara","lastName":"Siejak","gender":"k","age":54,"mail":"barbara.siejak@o2.pl","phoneNumber":"678-536-121","PESEL":"66122632569"},{"name":"Katarzyna","lastName":"Siejak","gender":"k","age":34,"mail":"katarzyna.siejak1@gmail.com","phoneNumber":"655-732-528","PESEL":"86122492264"},{"name":"Krzysztof","lastName":"Gromada","gender":"m","age":21,"mail":"gromada.krzysztof@onet.pl","phoneNumber":"024-771-061","PESEL":"99100724914"},{"name":"Krzysztof","lastName":"Waniorek","gender":"m","age":60,"mail":"krzysztof.waniorek@onet.pl","phoneNumber":"460-007-248","PESEL":"60100165793"},{"name":"Bartosz","lastName":"Gromada","gender":"m","age":34,"mail":"bartosz.gromada@wp.pl","phoneNumber":"458-336-837","PESEL":"86110896793"},{"name":"Barbara","lastName":"Gromada","gender":"k","age":41,"mail":"barbara.gromada@wp.pl","phoneNumber":"456-774-720","PESEL":"79071943963"},{"name":"Barbara","lastName":"Gromada","gender":"k","age":25,"mail":"barbara.gromada1@o2.pl","phoneNumber":"107-038-857","PESEL":"95063067462"},{"name":"Tomasz","lastName":"Waniorek","gender":"m","age":60,"mail":"tomasz.waniorek@gmail.com","phoneNumber":"430-303-816","PESEL":"60111626438"},{"name":"Katarzyna","lastName":"Siejak","gender":"k","age":53,"mail":"siejak.katarzyna@o2.pl","phoneNumber":"324-416-706","PESEL":"670619328810"},{"name":"Barbara","lastName":"Gromada","gender":"k","age":36,"mail":"gromada.barbara@gmail.com","phoneNumber":"104-555-836","PESEL":"84073042947"},{"name":"Joanna","lastName":"Waniorek","gender":"k","age":34,"mail":"waniorek.joanna@gmail.com","phoneNumber":"487-646-770","PESEL":"86042072924"},{"name":"Bartłomiej","lastName":"Waniorek","gender":"m","age":22,"mail":"waniorek.bartłomiej@gmail.com","phoneNumber":"772-747-134","PESEL":"98060498938"},{"name":"Joanna","lastName":"Waniorek","gender":"k","age":16,"mail":"joanna.waniorek1@onet.pl","phoneNumber":"447-213-171","PESEL":"04312854186"},{"name":"Tomasz","lastName":"Gromada","gender":"m","age":36,"mail":"tomasz.gromada@onet.pl","phoneNumber":"563-588-264","PESEL":"84120997453"},{"name":"Bartosz","lastName":"Siejak","gender":"m","age":39,"mail":"siejak.bartosz@onet.pl","phoneNumber":"065-342-605","PESEL":"81121297339"},{"name":"Joanna","lastName":"Waniorek","gender":"k","age":53,"mail":"joanna.waniorek2@onet.pl","phoneNumber":"608-801-461","PESEL":"670523584210"},{"name":"Krzysztof","lastName":"Siejak","gender":"m","age":46,"mail":"krzysztof.siejak1@onet.pl","phoneNumber":"534-344-852","PESEL":"74061754851"},{"name":"Barbara","lastName":"Siejak","gender":"k","age":19,"mail":"siejak.barbara@o2.pl","phoneNumber":"234-861-344","PESEL":"01312831506"},{"name":"Krzysztof","lastName":"Siejak","gender":"m","age":43,"mail":"krzysztof.siejak@wp.pl","phoneNumber":"383-884-411","PESEL":"770706244910"},{"name":"Barbara","lastName":"Gromada","gender":"k","age":35,"mail":"barbara.gromada1@gmail.com","phoneNumber":"302-644-622","PESEL":"85020692468"},{"name":"Krzysztof","lastName":"Gromada","gender":"m","age":43,"mail":"krzysztof.gromada1@onet.pl","phoneNumber":"331-133-835","PESEL":"77100862636"},{"name":"Krzysztof","lastName":"Gromada","gender":"m","age":54,"mail":"krzysztof.gromada@gmail.com","phoneNumber":"865-683-436","PESEL":"66091917137"},{"name":"Barbara","lastName":"Waniorek","gender":"k","age":51,"mail":"barbara.waniorek@gmail.com","phoneNumber":"616-841-764","PESEL":"69102467346"},{"name":"Bartłomiej","lastName":"Gromada","gender":"m","age":63,"mail":"bartłomiej.gromada@gmail.com","phoneNumber":"061-312-641","PESEL":"57111649437"},{"name":"Barbara","lastName":"Gromada","gender":"k","age":36,"mail":"barbara.gromada2@o2.pl","phoneNumber":"462-280-457","PESEL":"840626732610"},{"name":"Katarzyna","lastName":"Siejak","gender":"k","age":60,"mail":"katarzyna.siejak@wp.pl","phoneNumber":"801-776-223","PESEL":"60071728102"},{"name":"Joanna","lastName":"Waniorek","gender":"k","age":50,"mail":"joanna.waniorek@wp.pl","phoneNumber":"870-888-743","PESEL":"70091792221"},{"name":"Katarzyna","lastName":"Siejak","gender":"k","age":23,"mail":"katarzyna.siejak2@gmail.com","phoneNumber":"742-881-467","PESEL":"97032834345"},{"name":"Bartosz","lastName":"Waniorek","gender":"m","age":50,"mail":"bartosz.waniorek@o2.pl","phoneNumber":"623-457-061","PESEL":"70111339432"},{"name":"Bartłomiej","lastName":"Siejak","gender":"m","age":45,"mail":"siejak.bartłomiej@o2.pl","phoneNumber":"216-876-403","PESEL":"75102866436"},{"name":"Tomasz","lastName":"Siejak","gender":"m","age":21,"mail":"tomasz.siejak@gmail.com","phoneNumber":"216-230-088","PESEL":"990815481510"},{"name":"Barbara","lastName":"Gromada","gender":"k","age":31,"mail":"barbara.gromada3@o2.pl","phoneNumber":"374-581-200","PESEL":"89022445482"},{"name":"Barbara","lastName":"Gromada","gender":"k","age":29,"mail":"barbara.gromada2@gmail.com","phoneNumber":"350-522-046","PESEL":"91032615788"},{"name":"Joanna","lastName":"Gromada","gender":"k","age":31,"mail":"gromada.joanna@wp.pl","phoneNumber":"483-325-126","PESEL":"89111551306"},{"name":"Bartosz","lastName":"Siejak","gender":"m","age":39,"mail":"bartosz.siejak1@onet.pl","phoneNumber":"378-136-486","PESEL":"810916785110"},{"name":"Katarzyna","lastName":"Gromada","gender":"k","age":47,"mail":"katarzyna.gromada1@o2.pl","phoneNumber":"675-638-587","PESEL":"73020196709"},{"name":"Barbara","lastName":"Waniorek","gender":"k","age":61,"mail":"waniorek.barbara@wp.pl","phoneNumber":"544-683-760","PESEL":"59111997367"},{"name":"Joanna","lastName":"Waniorek","gender":"k","age":20,"mail":"joanna.waniorek@o2.pl","phoneNumber":"221-674-445","PESEL":"000227832810"},{"name":"Krzysztof","lastName":"Gromada","gender":"m","age":60,"mail":"krzysztof.gromada@o2.pl","phoneNumber":"465-548-017","PESEL":"60090163339"},{"name":"Joanna","lastName":"Gromada","gender":"k","age":15,"mail":"joanna.gromada@onet.pl","phoneNumber":"684-422-744","PESEL":"05260624405"},{"name":"Joanna","lastName":"Waniorek","gender":"k","age":48,"mail":"waniorek.joanna@o2.pl","phoneNumber":"204-768-243","PESEL":"72070835226"},{"name":"Joanna","lastName":"Gromada","gender":"k","age":18,"mail":"joanna.gromada@gmail.com","phoneNumber":"557-036-531","PESEL":"02280552109"},{"name":"Barbara","lastName":"Siejak","gender":"k","age":35,"mail":"barbara.siejak@onet.pl","phoneNumber":"566-854-160","PESEL":"85020259809"},{"name":"Tomasz","lastName":"Gromada","gender":"m","age":63,"mail":"tomasz.gromada@gmail.com","phoneNumber":"218-273-334","PESEL":"57032638295"},{"name":"Tomasz","lastName":"Waniorek","gender":"m","age":36,"mail":"tomasz.waniorek@o2.pl","phoneNumber":"068-078-443","PESEL":"84071777676"}]